openssa/Makefile
openssa/README.md
openssa/__init__.py
openssa/contrib/__init__.py
openssa/contrib/streamlit_ssa_prob_solver/.gitignore
openssa/contrib/streamlit_ssa_prob_solver/.streamlit/secrets.toml.template
openssa/contrib/streamlit_ssa_prob_solver/Makefile
openssa/contrib/streamlit_ssa_prob_solver/__init__.py
openssa/contrib/streamlit_ssa_prob_solver/main.py
openssa/contrib/streamlit_ssa_prob_solver/pages/Semiconductor_ALD_SSA.py
openssa/contrib/streamlit_ssa_prob_solver/pages/Your_SSA_#1.py
openssa/contrib/streamlit_ssa_prob_solver/pages/Your_SSA_#2.py
openssa/contrib/streamlit_ssa_prob_solver/pages/Your_SSA_#3.py
openssa/contrib/streamlit_ssa_prob_solver/requirements.txt
openssa/core/__tmp__.py
openssa/core/agent/dana.py
openssa/core/knowledge/_prompts.py
openssa/core/knowledge/base.py
openssa/core/knowledge/fact/base.py
openssa/core/knowledge/heuristic/base.py
openssa/core/knowledge/inference_rule/base.py
openssa/core/program_store/_prompts.py
openssa/core/program_store/program_store.py
openssa/core/programming/__tmp__.py
openssa/core/programming/base/program.py
openssa/core/programming/base/programmer.py
openssa/core/programming/hierarchical/_prompts.py
openssa/core/programming/hierarchical/plan.py
openssa/core/programming/hierarchical/planner.py
openssa/core/reasoning/base.py
openssa/core/reasoning/ooda/_prompts.py
openssa/core/reasoning/ooda/ooda_reasoner.py
openssa/core/reasoning/simple/_prompts.py
openssa/core/reasoning/simple/simple_reasoner.py
openssa/core/resource/_global.py
openssa/core/resource/_prompts.py
openssa/core/resource/base.py
openssa/core/resource/db.py
openssa/core/resource/file.py
openssa/core/resource/rss.py
openssa/core/resource/sensor.py
openssa/core/resource/web.py
openssa/core/task/nature.py
openssa/core/task/status.py
openssa/core/task/task.py
openssa/core/util/lm/base.py
openssa/core/util/lm/config.py
openssa/core/util/lm/huggingface.py
openssa/core/util/lm/llama.py
openssa/core/util/lm/openai.py
openssa/core/util/misc.py
openssa-0.24.12.12.dist-info/LICENSE.md
openssa-0.24.12.12.dist-info/METADATA
openssa-0.24.12.12.dist-info/WHEEL
openssa-0.24.12.12.dist-info/RECORD
