Metadata-Version: 2.1
Name: openssa
Version: 0.24.12.12
Summary: OpenSSA: Small Specialist Agents for Industrial AI
Home-page: https://openssa.org
License: Apache-2.0
Keywords: Artificial Intelligence,A.I.,AI,industrial,specialist,specialized,domain,expertise,knowledge
Author: Aitomatic, Inc.
Author-email: engineering@aitomatic.com
Maintainer: Aitomatic, Inc.
Maintainer-email: engineering@aitomatic.com
Requires-Python: >=3.12,<3.14
Classifier: License :: OSI Approved :: Apache Software License
Classifier: Programming Language :: Python :: 3
Classifier: Programming Language :: Python :: 3.12
Classifier: Programming Language :: Python :: 3.13
Provides-Extra: contrib
Provides-Extra: langchain
Requires-Dist: adlfs (>=2024.7)
Requires-Dist: certifi (>2024.12)
Requires-Dist: docx2txt (>=0.8)
Requires-Dist: faiss-cpu (>=1.9) ; extra == "langchain"
Requires-Dist: fsspec (>=2024.10)
Requires-Dist: gcsfs (>=2024.10)
Requires-Dist: google-api-python-client (>=2.155)
Requires-Dist: googlesearch-python (>=1.2)
Requires-Dist: httpx (>=0.28)
Requires-Dist: huggingface-hub (>=0.26)
Requires-Dist: langchainhub (>=0.1) ; extra == "langchain"
Requires-Dist: llama-index (>=0.12)
Requires-Dist: llama-index-embeddings-azure-openai (>=0.3)
Requires-Dist: llama-index-llms-azure-openai (>=0.3)
Requires-Dist: llama-index-readers-web (>=0.3)
Requires-Dist: loguru (>=0.7)
Requires-Dist: openai (>=1.57)
Requires-Dist: pycryptodome (>=3.21)
Requires-Dist: pydantic (>=2.10)
Requires-Dist: pypdf (>=5.1)
Requires-Dist: python-dotenv (>=1.0)
Requires-Dist: s3fs (>=2024.10)
Requires-Dist: streamlit (>=1.41) ; extra == "contrib"
Requires-Dist: streamlit-extras (>=0.5) ; extra == "contrib"
Requires-Dist: streamlit-mic-recorder (>=0.0.8) ; extra == "contrib"
Requires-Dist: tqdm (>=4.67)
Project-URL: Documentation, https://aitomatic.github.io/openssa
Project-URL: Repository, https://github.com/aitomatic/openssa
